{"cameraMode":{"drawMode":0,"name":"Shaded","section":"Shading Mode"},"sceneLighting":true,"audioPlay":false,"sceneViewState":{"m_AlwaysRefresh":false,"showFog":true,"showSkybox":true,"showFlares":true,"showImageEffects":true,"showParticleSystems":true,"showVisualEffectGraphs":true,"m_FxEnabled":true},"in2DMode":false,"pivot":{"x":-0.05064582824707031,"y":-0.1764359474182129,"z":-0.12822246551513673},"rotation":{"x":-0.17006391286849976,"y":0.6320980787277222,"z":-0.14487771689891816,"w":-0.7419848442077637},"size":7.586129188537598,"orthographic":false}